opentelemetry/util/genai/__init__.py
opentelemetry/util/genai/completion_hook.py
opentelemetry/util/genai/environment_variables.py
opentelemetry/util/genai/types.py
opentelemetry/util/genai/utils.py
opentelemetry/util/genai/version.py
opentelemetry/util/genai/_fsspec_upload/__init__.py
opentelemetry/util/genai/_fsspec_upload/completion_hook.py
opentelemetry_util_genai-0.1b0.dist-info/METADATA
opentelemetry_util_genai-0.1b0.dist-info/WHEEL
opentelemetry_util_genai-0.1b0.dist-info/entry_points.txt
opentelemetry_util_genai-0.1b0.dist-info/licenses/LICENSE
opentelemetry_util_genai-0.1b0.dist-info/RECORD
