Metadata-Version: 2.4
Name: opentelemetry-util-genai
Version: 0.1b0
Summary: OpenTelemetry GenAI Utils
Project-URL: Homepage, https://github.com/open-telemetry/opentelemetry-python-contrib/tree/main/util/opentelemetry-util-genai
Project-URL: Repository, https://github.com/open-telemetry/opentelemetry-python-contrib
Author-email: OpenTelemetry Authors <cncf-opentelemetry-contributors@lists.cncf.io>
License-Expression: Apache-2.0
License-File: LICENSE
Classifier: Development Status :: 4 - Beta
Classifier: Intended Audience :: Developers
Classifier: License :: OSI Approved :: Apache Software License
Classifier: Programming Language :: Python
Classifier: Programming Language :: Python :: 3
Classifier: Programming Language :: Python :: 3.9
Classifier: Programming Language :: Python :: 3.10
Classifier: Programming Language :: Python :: 3.11
Classifier: Programming Language :: Python :: 3.12
Classifier: Programming Language :: Python :: 3.13
Requires-Python: >=3.8
Requires-Dist: opentelemetry-api>=1.31.0
Requires-Dist: opentelemetry-instrumentation~=0.51b0
Requires-Dist: opentelemetry-semantic-conventions~=0.51b0
Provides-Extra: fsspec
Requires-Dist: fsspec>=2025.9.0; extra == 'fsspec'
Provides-Extra: test
Requires-Dist: pytest>=7.0.0; extra == 'test'
